opencovid19_api/__init__.py
opencovid19_api-0.0.1.dist-info/LICENSE
opencovid19_api-0.0.1.dist-info/WHEEL
opencovid19_api-0.0.1.dist-info/METADATA
opencovid19_api-0.0.1.dist-info/RECORD
