Metadata-Version: 2.1
Name: opencovid19-api
Version: 0.0.1
Summary: OpenCOVID-19 API for COVID-19 Data
Home-page: https://github.com/opencovid19data/opencovid19-api
Author: OpenCOVID-19
Requires-Python: >=3.7,<4.0
Classifier: Programming Language :: Python :: 3
Classifier: Programming Language :: Python :: 3.10
Classifier: Programming Language :: Python :: 3.7
Classifier: Programming Language :: Python :: 3.8
Classifier: Programming Language :: Python :: 3.9
Project-URL: Repository, https://github.com/opencovid19data/opencovid19-api
